django_xmlrpc_dx/__init__.py
django_xmlrpc_dx/apps.py
django_xmlrpc_dx/decorators.py
django_xmlrpc_dx/dispatcher.py
django_xmlrpc_dx/registry.py
django_xmlrpc_dx/views.py
django_xmlrpc_dx/locale/fr/LC_MESSAGES/django.mo
django_xmlrpc_dx/locale/fr/LC_MESSAGES/django.po
django_xmlrpc_dx/templates/xmlrpc_get.html
django_xmlrpc_dx-0.1.10.dist-info/licenses/LICENSE
django_xmlrpc_dx-0.1.10.dist-info/METADATA
django_xmlrpc_dx-0.1.10.dist-info/WHEEL
django_xmlrpc_dx-0.1.10.dist-info/top_level.txt
django_xmlrpc_dx-0.1.10.dist-info/RECORD
