Metadata-Version: 2.4
Name: django-xmlrpc-dx
Version: 0.1.10
Summary: XML-RPC Server App for the Django framework.
Home-page: https://github.com/rubeon/django-xmlrpc
Author: rubeon
Author-email: rubeon@gmail.com
Maintainer: rubeon
Maintainer-email: rubeon@gmail.com
License: New BSD License
Keywords: django,service,xmlrpc
Classifier: Framework :: Django
Classifier: Development Status :: 5 - Production/Stable
Classifier: Environment :: Web Environment
Classifier: Programming Language :: Python
Classifier: Programming Language :: Python :: 3
Classifier: Intended Audience :: Developers
Classifier: Operating System :: OS Independent
Classifier: Topic :: Software Development :: Libraries :: Python Modules
License-File: LICENSE
Dynamic: author
Dynamic: author-email
Dynamic: classifier
Dynamic: description
Dynamic: home-page
Dynamic: keywords
Dynamic: license
Dynamic: license-file
Dynamic: maintainer
Dynamic: maintainer-email
Dynamic: summary
